README.md
setup.py
astanczyk_hello_world.egg-info/PKG-INFO
astanczyk_hello_world.egg-info/SOURCES.txt
astanczyk_hello_world.egg-info/dependency_links.txt
astanczyk_hello_world.egg-info/top_level.txt
sample_package/__init__.py
sample_package/sample.py