Metadata-Version: 2.1
Name: astanczyk-hello-world
Version: 1.0.0
Summary: Sample PYPI App
Home-page: UNKNOWN
License: UNKNOWN
Platform: UNKNOWN
